ai_interviewer/database/__init__.py
ai_interviewer/database/db_handler.py
ai_interviewer/database/models.py
ai_interviewer/llm/__init__.py
ai_interviewer/llm/api_llm.py
ai_interviewer/llm/claude_llm.py
ai_interviewer/llm/gigachat_llm.py
ai_interviewer/llm/llama_llm.py
ai_interviewer/llm/mistral_api_llm.py
ai_interviewer/llm/mistral_llm.py
ai_interviewer/llm/openai_llm.py
ai_interviewer/llm/yandex_llm.py
ai_interviewer/stt/__init__.py
ai_interviewer/stt/amazon_transcribe.py
ai_interviewer/stt/api_stt.py
ai_interviewer/stt/google_stt.py
ai_interviewer/stt/vosk_stt.py
ai_interviewer/stt/whisper_stt.py
ai_interviewer/tts/__init__.py
ai_interviewer/tts/amazon_polly.py
ai_interviewer/tts/api_tts.py
ai_interviewer/tts/edge_tts.py
ai_interviewer/tts/elevenlabs.py
ai_interviewer/tts/google_tts.py
ai_interviewer/utils/__init__.py
ai_interviewer/utils/audio_recorder.py
ai_interviewer/utils/downloader.py
ai_interviewer/utils/launcher.py
ai_interviewer/utils/llm_evaluator.py
ai_interviewer/utils/prompt_generator.py
ai_interviewer/utils/question_manager.py
ai_interviewer/utils/stat_evaluator.py
ai_interviewer-0.1.0.dist-info/METADATA
ai_interviewer-0.1.0.dist-info/WHEEL
ai_interviewer-0.1.0.dist-info/RECORD
