Metadata-Version: 2.3
Name: ai-interviewer
Version: 0.1.0
Summary: AI-powered technical interview simulator with adaptive questioning and evaluation
Author: Sergey Volkov
Requires-Python: >=3.13
Classifier: Programming Language :: Python :: 3
Classifier: Programming Language :: Python :: 3.13
